{"AOR":{"name":"กวานซารีจัสทาโดแองโกลา (1995–1999)"},"AOA":{"name":"กวานซาแองโกลา","symbolNarrow":"Kz"},"AOK":{"name":"กวานซาแองโกลา (1977–1990)"},"PYG":{"name":"กวารานีปารากวัย","symbolNarrow":"₲"},"XRE":{"name":"กองทุนไรเน็ต"},"NIO":{"name":"กอร์โดบานิการากัว","symbolNarrow":"C$"},"SRG":{"name":"กิลเดอร์ซูรินาเม"},"NLG":{"name":"กิลเดอร์เนเธอร์แลนด์"},"ANG":{"name":"กิลเดอร์เนเธอร์แลนด์แอนทิลลิส"},"PGK":{"name":"กีนาปาปัวนิวกินี"},"LAK":{"name":"กีบลาว","symbolNarrow":"₭"},"HTG":{"name":"กูร์ดเฮติ"},"CRC":{"name":"โกลองคอสตาริกา","symbolNarrow":"₡"},"BRN":{"name":"ครูซาโดโนโวบราซิล"},"BRC":{"name":"ครูซาโดบราซิล"},"BRB":{"name":"ครูเซโรโนโวบราซิล (1967–1986)"},"BRR":{"name":"ครูเซโรบราซิล"},"BRZ":{"name":"ครูเซโรบราซิล (1942–1967)"},"BRE":{"name":"ครูเซโรบราซิล (1990–1993)"},"EEK":{"name":"ครูนเอสโตเนีย"},"ZMW":{"name":"ควาชาแซมเบีย","symbolNarrow":"ZK"},"ZMK":{"name":"ควาชาแซมเบีย (1968–2012)"},"MWK":{"name":"ควาชามาลาวี"},"YUN":{"name":"คอนเวอร์ทิเบิลดีนาร์ยูโกสลาเวีย"},"LUC":{"name":"คอนเวอร์ทิเบิลฟรังก์ลักเซมเบิร์ก"},"NIC":{"name":"คอร์โดบานิการากัว"},"UAK":{"name":"คาร์โบวาเนตซ์ยูเครน"},"HRK":{"name":"คูนาโครเอเชีย","symbolNarrow":"kn"},"GEK":{"name":"คูปอนลาริตจอร์เจีย"},"GTQ":{"name":"เควตซัลกัวเตมาลา","symbolNarrow":"Q"},"DKK":{"name":"โครนเดนมาร์ก","symbolNarrow":"kr"},"NOK":{"name":"โครนนอร์เวย์","symbolNarrow":"kr"},"SEK":{"name":"โครนาสวีเดน","symbolNarrow":"kr"},"ISK":{"name":"โครนาไอซ์แลนด์","symbolNarrow":"kr"},"SKK":{"name":"โครูนาสโลวัก"},"CZK":{"name":"โครูนาสาธารณรัฐเช็ก","symbolNarrow":"Kč"},"SVC":{"name":"โคลอนเอลซัลวาดอร์"},"XAG":{"name":"เงิน"},"MXP":{"name":"เงินเปโซเม็กซิโก (1861–1992)"},"BUK":{"name":"จ๊าดพม่า"},"MMK":{"name":"จ๊าตพม่า","symbolNarrow":"K"},"KES":{"name":"ชิลลิงเคนยา"},"SOS":{"name":"ชิลลิงโซมาเลีย"},"TZS":{"name":"ชิลลิงแทนซาเนีย"},"UGX":{"name":"ชิลลิงยูกันดา"},"UGS":{"name":"ชิลลิงยูกันดา (1966–1987)"},"ATS":{"name":"ชิลลิงออสเตรีย"},"PLN":{"name":"ซลอตีโปแลนด์","symbolNarrow":"zł"},"PLZ":{"name":"ซลอตีโปแลนด์ (1950–1995)"},"KGS":{"name":"ซอมคีร์กีซสถาน"},"UZS":{"name":"ซอมอุซเบกิสถาน"},"PEN":{"name":"ซอลเปรู"},"PES":{"name":"ซอลเปรู (1863–1965)","pluralName":{"other":"ซอลเปรู(1863–1965)"}},"XSU":{"name":"ซูเกร"},"ECS":{"name":"ซูเกรเอกวาดอร์"},"GHS":{"name":"เซดีกานา"},"GHC":{"name":"เซดีกานา (1979–2007)"},"ZRZ":{"name":"แซร์คองโก"},"BGM":{"name":"โซเชียลลิสต์เลฟบัลแกเรีย"},"TJS":{"name":"โซโมนิทาจิกิสถาน"},"GNS":{"name":"ไซลีกินี"},"GRD":{"name":"ดรัชมากรีก"},"VND":{"symbol":"₫","name":"ดองเวียดนาม","symbolNarrow":"₫"},"VNN":{"name":"ดองเวียดนาม (1978–1985)"},"STD":{"name":"ดอบราเซาตูเมและปรินซิปี","symbolNarrow":"Db"},"GYD":{"name":"ดอลลาร์กายอานา","symbolNarrow":"$"},"CAD":{"symbol":"CA$","name":"ดอลลาร์แคนาดา","symbolNarrow":"$"},"XCD":{"symbol":"EC$","name":"ดอลลาร์แคริบเบียนตะวันออก","symbolNarrow":"$"},"JMD":{"name":"ดอลลาร์จาเมกา","symbolNarrow":"$"},"ZWD":{"name":"ดอลลาร์ซิมบับเว"},"ZWR":{"name":"ดอลลาร์ซิมบับเว (2008)"},"ZWL":{"name":"ดอลลาร์ซิมบับเว (2009)"},"SRD":{"name":"ดอลลาร์ซูรินาเม","symbolNarrow":"$"},"TTD":{"name":"ดอลลาร์ตรินิแดดและโตเบโก","symbolNarrow":"$"},"TWD":{"symbol":"NT$","name":"ดอลลาร์ไต้หวันใหม่","symbolNarrow":"NT$"},"NAD":{"name":"ดอลลาร์นามิเบีย","symbolNarrow":"$"},"NZD":{"symbol":"NZ$","name":"ดอลลาร์นิวซีแลนด์","symbolNarrow":"$"},"BND":{"name":"ดอลลาร์บรูไน","symbolNarrow":"$"},"BBD":{"name":"ดอลลาร์บาร์เบโดส","symbolNarrow":"$"},"BSD":{"name":"ดอลลาร์บาฮามาส","symbolNarrow":"$"},"BZD":{"name":"ดอลลาร์เบลีซ","symbolNarrow":"$"},"BMD":{"name":"ดอลลาร์เบอร์มิวดา","symbolNarrow":"$"},"FJD":{"name":"ดอลลาร์ฟิจิ","symbolNarrow":"$"},"RHD":{"name":"ดอลลาร์โรดีเซีย"},"LRD":{"name":"ดอลลาร์ไลบีเรีย","symbolNarrow":"$"},"USD":{"symbol":"US$","name":"ดอลลาร์สหรัฐ","symbolNarrow":"$"},"USS":{"name":"ดอลลาร์สหรัฐ (วันเดียวกัน)"},"USN":{"name":"ดอลลาร์สหรัฐ (วันถัดไป)"},"SGD":{"name":"ดอลลาร์สิงคโปร์","symbolNarrow":"$"},"KYD":{"name":"ดอลลาร์หมู่เกาะเคย์แมน","symbolNarrow":"$"},"SBD":{"name":"ดอลลาร์หมู่เกาะโซโลมอน","symbolNarrow":"$"},"AUD":{"symbol":"AU$","name":"ดอลลาร์ออสเตรเลีย","symbolNarrow":"$"},"HKD":{"symbol":"HK$","name":"ดอลลาร์ฮ่องกง","symbolNarrow":"$"},"GMD":{"name":"ดาลาซีแกมเบีย"},"KWD":{"name":"ดีนาร์คูเวต"},"HRD":{"name":"ดีนาร์โครเอเชีย"},"JOD":{"name":"ดีนาร์จอร์แดน"},"SDD":{"name":"ดีนาร์ซูดานเก่า"},"RSD":{"name":"ดีนาร์เซอร์เบีย"},"CSD":{"name":"ดีนาร์เซอร์เบียเก่า"},"TND":{"name":"ดีนาร์ตูนิเซีย"},"BAD":{"name":"ดีนาร์บอสเนีย-เฮอร์เซโกวีนา"},"BHD":{"name":"ดีนาร์บาห์เรน"},"YUR":{"name":"ดีนาร์ปฏิรูปยูโกสลาเวีย (1992–1993)"},"MKD":{"name":"ดีนาร์มาซิโดเนีย"},"MKN":{"name":"ดีนาร์มาซิโดเนีย (1992–1993)"},"YDD":{"name":"ดีนาร์เยเมน"},"LYD":{"name":"ดีนาร์ลิเบีย"},"BAN":{"name":"ดีนาร์ใหม่บอสเนีย-เฮอร์เซโกวีนา (1994–1997)"},"IQD":{"name":"ดีนาร์อิรัก"},"DZD":{"name":"ดีนาร์แอลจีเรีย"},"MAD":{"name":"ดีแรห์มโมร็อกโก"},"AED":{"name":"เดอร์แฮมสหรัฐอาหรับเอมิเรตส์"},"AMD":{"name":"แดรมอาร์เมเนีย"},"BDT":{"name":"ตากาบังกลาเทศ","symbolNarrow":"৳"},"XAU":{"name":"ทอง"},"SIT":{"name":"ทอลาร์สโลวีเนีย"},"WST":{"name":"ทาลาซามัว"},"LTT":{"name":"ทาโลนัสลิทัวเนีย"},"MNT":{"name":"ทูกริกมองโกเลีย","symbolNarrow":"₮"},"KZT":{"name":"เทงเจคาซัคสถาน","symbolNarrow":"₸"},"AON":{"name":"นิวกวานซาแองโกลา (1990–2000)"},"ILS":{"symbol":"₪","name":"นิวเชเกลอิสราเอล","symbolNarrow":"₪"},"ZRN":{"name":"นิวแซร์คองโก"},"BYB":{"name":"นิวรูเบิลเบลารุส (1994–1999)"},"ERN":{"name":"แนกฟาเอริเทรีย"},"YUM":{"name":"โนวิย์ดีนาร์ยูโกสลาเวีย"},"NGN":{"name":"ไนราไนจีเรีย","symbolNarrow":"₦"},"MDC":{"name":"บัตรปันส่วนมอลโดวา"},"PAB":{"name":"บัลบัวปานามา"},"THB":{"name":"บาทไทย","symbolNarrow":"฿"},"ETB":{"name":"เบอรร์เอธิโอเปีย"},"VEF":{"name":"โบลิวาร์เวเนซุเอลา","symbolNarrow":"Bs"},"VEB":{"name":"โบลิวาร์เวเนซุเอลา (1871–2008)"},"BOB":{"name":"โบลิเวียโนโบลิเวีย","symbolNarrow":"Bs"},"BOL":{"name":"โบลิเวียโนโบลิเวีย (1863–1963)"},"SYP":{"name":"ปอนด์ซีเรีย","symbolNarrow":"£"},"SDG":{"name":"ปอนด์ซูดาน"},"SDP":{"name":"ปอนด์ซูดานเก่า"},"SSP":{"name":"ปอนด์ซูดานใต้","symbolNarrow":"£"},"SHP":{"name":"ปอนด์เซนต์เฮเลนา","symbolNarrow":"£"},"CYP":{"name":"ปอนด์ไซปรัส"},"MTP":{"name":"ปอนด์มอลตา"},"GIP":{"name":"ปอนด์ยิบรอลตาร์","symbolNarrow":"£"},"LBP":{"name":"ปอนด์เลบานอน","symbolNarrow":"L£"},"GBP":{"symbol":"£","name":"ปอนด์สเตอร์ลิง (สหราชอาณาจักร)","symbolNarrow":"£"},"FKP":{"name":"ปอนด์หมู่เกาะฟอล์กแลนด์","symbolNarrow":"£"},"ILP":{"name":"ปอนด์อิสราเอล"},"EGP":{"name":"ปอนด์อียิปต์","symbolNarrow":"E£"},"IEP":{"name":"ปอนด์ไอริช"},"MOP":{"name":"ปาตากามาเก๊า"},"BWP":{"name":"ปูลาบอตสวานา","symbolNarrow":"P"},"ESP":{"name":"เปเซตาสเปน","symbolNarrow":"₧"},"ESB":{"name":"เปเซตาสเปน (บัญชีที่เปลี่ยนแปลงได้)"},"ESA":{"name":"เปเซตาสเปน (บัญชีเอ)"},"ADP":{"name":"เปเซตาอันดอร์รา"},"GWP":{"name":"เปโซกินี-บิสเซา"},"CUP":{"name":"เปโซคิวบา","symbolNarrow":"$"},"CUC":{"name":"เปโซคิวบา (แปลงสภาพ)","symbolNarrow":"$"},"COP":{"name":"เปโซโคลอมเบีย","symbolNarrow":"$"},"CLP":{"name":"เปโซชิลี","symbolNarrow":"$"},"DOP":{"name":"เปโซโดมินิกัน","symbolNarrow":"$"},"BOP":{"name":"เปโซโบลิเวีย"},"PHP":{"name":"เปโซฟิลิปปินส์","symbolNarrow":"₱"},"MXN":{"symbol":"MX$","name":"เปโซเม็กซิโก","symbolNarrow":"$"},"ARL":{"name":"เปโซเลย์อาร์เจนตินา (1970–1983)"},"ARS":{"name":"เปโซอาร์เจนตินา","symbolNarrow":"$"},"ARM":{"name":"เปโซอาร์เจนตินา (1881–1970)"},"ARP":{"name":"เปโซอาร์เจนตินา (1983–1985)"},"UYU":{"name":"เปโซอุรุกวัย","symbolNarrow":"$"},"UYP":{"name":"เปโซอุรุกวัย (1975–1993)"},"UYI":{"name":"เปโซเอนยูนิแดดเซสอินเด็กซาแดสอุรุกวัย"},"XPD":{"name":"พัลเลเดียม"},"TOP":{"name":"พาแองกาตองกา","symbolNarrow":"T$"},"XPT":{"name":"แพลตินัม"},"GNF":{"name":"ฟรังก์กินี","symbolNarrow":"FG"},"CDF":{"name":"ฟรังก์คองโก"},"KMF":{"name":"ฟรังก์คอโมโรส","symbolNarrow":"CF"},"DJF":{"name":"ฟรังก์จิบูตี"},"XPF":{"symbol":"CFPF","name":"ฟรังก์ซีเอฟพี"},"XOF":{"symbol":"CFA","name":"ฟรังก์เซฟาธนาคารกลางรัฐแอฟริกาตะวันตก"},"XAF":{"symbol":"FCFA","name":"ฟรังก์เซฟาธนาคารรัฐแอฟริกากลาง"},"CHW":{"name":"ฟรังก์ดับเบิลยูไออาร์"},"XFO":{"name":"ฟรังก์ทองฝรั่งเศส"},"BIF":{"name":"ฟรังก์บุรุนดี"},"BEF":{"name":"ฟรังก์เบลเยียม"},"BEL":{"name":"ฟรังก์เบลเยียม (การเงิน)"},"BEC":{"name":"ฟรังก์เบลเยียม (เปลี่ยนแปลงได้)"},"FRF":{"name":"ฟรังก์ฝรั่งเศส"},"MGF":{"name":"ฟรังก์มาดากัสการ์"},"MLF":{"name":"ฟรังก์มาลี"},"MCF":{"name":"ฟรังก์โมนาโก"},"MAF":{"name":"ฟรังก์โมร็อกโก"},"XFU":{"name":"ฟรังก์ยูไอซีฝรั่งเศส"},"RWF":{"name":"ฟรังก์รวันดา","symbolNarrow":"RF"},"LUF":{"name":"ฟรังก์ลักเซมเบิร์ก"},"CHF":{"name":"ฟรังก์สวิส"},"AWG":{"name":"ฟลอรินอารูบา"},"HUF":{"name":"ฟอรินต์ฮังการี","symbolNarrow":"Ft"},"CLF":{"name":"ฟูเมนโตชิลี"},"LUL":{"name":"ไฟแนลเชียลฟรังก์ลักเซมเบิร์ก"},"BOV":{"name":"มฟดอลโบลิเวีย"},"TMT":{"name":"มานัตเติร์กเมนิสถาน"},"TMM":{"name":"มานัตเติร์กเมนิสถาน (1993–2009)"},"AZN":{"name":"มานัตอาเซอร์ไบจาน"},"AZM":{"name":"มานัตอาเซอร์ไบจาน (1993–2006)"},"FIM":{"name":"มาร์กกาฟินแลนด์"},"BAM":{"name":"มาร์กบอสเนีย-เฮอร์เซโกวีนา","symbolNarrow":"KM"},"DEM":{"name":"มาร์กเยอรมัน"},"DDM":{"name":"มาร์กเยอรมันตะวันออก"},"MZN":{"name":"เมติคัลโมซัมบิก"},"MZM":{"name":"เมติคัลโมซัมบิกเก่า"},"MXV":{"name":"ยูนิแดด ดี อินเวอร์ชั่น เม็กซิโก"},"EUR":{"symbol":"€","name":"ยูโร","symbolNarrow":"€"},"CHE":{"name":"ยูโรดับเบิลยูไออาร์"},"JPY":{"symbol":"¥","name":"เยนญี่ปุ่น","symbolNarrow":"¥"},"XTS":{"name":"รหัสทดสอบสกุลเงิน"},"MYR":{"name":"ริงกิตมาเลเซีย","symbolNarrow":"RM"},"SAR":{"name":"ริยัลซาอุดีอาระเบีย"},"SUR":{"name":"รูเบิลโซเวียต"},"TJR":{"name":"รูเบิลทาจิกิสถาน"},"BYN":{"name":"รูเบิลเบลารุส","symbolNarrow":"р."},"BYR":{"name":"รูเบิลเบลารุส (2000–2016)"},"RUB":{"name":"รูเบิลรัสเซีย","symbolNarrow":"₽","symbolAlt":"₽"},"RUR":{"name":"รูเบิลรัสเซีย (1991–1998)","symbolNarrow":"р."},"LVR":{"name":"รูเบิลลัตเวีย"},"SCR":{"name":"รูปีเซเชลส์"},"NPR":{"name":"รูปีเนปาล","symbolNarrow":"Rs"},"PKR":{"name":"รูปีปากีสถาน","symbolNarrow":"Rs"},"MUR":{"name":"รูปีมอริเชียส","symbolNarrow":"Rs"},"LKR":{"name":"รูปีศรีลังกา","symbolNarrow":"Rs"},"INR":{"symbol":"₹","name":"รูปีอินเดีย","symbolNarrow":"₹"},"IDR":{"name":"รูเปียห์อินโดนีเซีย","symbolNarrow":"Rp"},"MVR":{"name":"รูฟิยามัลดีฟส์"},"KHR":{"name":"เรียลกัมพูชา","symbolNarrow":"៛"},"QAR":{"name":"เรียลกาตาร์"},"BRL":{"symbol":"R$","name":"เรียลบราซิล","symbolNarrow":"R$"},"YER":{"name":"เรียลเยเมน"},"IRR":{"name":"เรียลอิหร่าน"},"OMR":{"name":"เรียลโอมาน"},"ZAR":{"name":"แรนด์แอฟริกาใต้","symbolNarrow":"R"},"ZAL":{"name":"แรนด์แอฟริกาใต้ (การเงิน)"},"LVL":{"name":"ลัตส์ลัตเวีย","symbolNarrow":"Ls"},"GEL":{"name":"ลารีจอร์เจีย","symbolNarrow":"₾","symbolAlt":"₾"},"SZL":{"name":"ลิลันเจนีสวาซิ"},"MDL":{"name":"ลิวมอลโดวา"},"RON":{"name":"ลิวโรมาเนีย","symbolNarrow":"lei"},"ROL":{"name":"ลิวโรมาเนียเก่า"},"LTL":{"name":"ลีตัสลิทัวเนีย","symbolNarrow":"Lt"},"TRY":{"name":"ลีราตุรกี","symbolNarrow":"₺","symbolAlt":"TL"},"TRL":{"name":"ลีราตุรกีเก่า"},"MTL":{"name":"ลีรามอลตา"},"ITL":{"name":"ลีราอิตาลี"},"SLL":{"name":"ลีโอนเซียร์ราลีโอน"},"ALL":{"name":"เลกแอลเบเนีย"},"BGO":{"name":"เลฟบัลเกเรีย (1879–1952)"},"BGN":{"name":"เลฟบัลแกเรีย"},"HNL":{"name":"เลมปิราฮอนดูรัส","symbolNarrow":"L"},"LSL":{"name":"โลตีเลโซโท"},"KRW":{"symbol":"₩","name":"วอนเกาหลีใต้","symbolNarrow":"₩"},"KRO":{"name":"วอนเกาหลีใต้ (1945–1953)"},"KPW":{"name":"วอนเกาหลีเหนือ","symbolNarrow":"₩"},"VUV":{"name":"วาตูวานูอาตู"},"ECV":{"name":"วาเลอร์คอนสแตนต์เอกวาดอร์"},"COU":{"name":"วาเลอร์เรียลโคลอมเบีย"},"XXX":{"name":"สกุลเงินที่ไม่รู้จัก","pluralName":{"other":"(สกุลเงินที่ไม่รู้จัก)"}},"XDR":{"name":"สิทธิถอนเงินพิเศษ"},"XBA":{"name":"หน่วยคอมโพสิตยุโรป"},"XBC":{"name":"หน่วยบัญชียุโรป [XBC]"},"XBD":{"name":"หน่วยบัญชียุโรป [XBD]"},"XUA":{"name":"หน่วยบัญชี เอดีบี"},"XBB":{"name":"หน่วยโมเนทารียุโรป"},"XEU":{"name":"หน่วยสกุลเงินยุโรป"},"CNY":{"symbol":"CN¥","name":"หยวนจีน","symbolNarrow":"¥"},"ARA":{"name":"ออสตรัลอาร์เจนตินา"},"AFN":{"name":"อัฟกานิอัฟกานิสถาน"},"AFA":{"name":"อัฟกานีอัฟกานิสถาน (1927–2002)"},"MGA":{"name":"อาเรียรีมาลากาซี","symbolNarrow":"Ar"},"PEI":{"name":"อินตีเปรู"},"MRO":{"name":"อูกียามอริเตเนีย"},"GQE":{"name":"เอ็กเวเลอิเควทอเรียลกินี"},"BTN":{"name":"เอ็งกุลตรัมภูฏาน"},"GWE":{"name":"เอสคูโดกินีโปรตุเกส"},"CVE":{"name":"เอสคูโดเคปเวิร์ด"},"CLE":{"name":"เอสคูโดชิลี"},"TPE":{"name":"เอสคูโดติมอร์"},"PTE":{"name":"เอสคูโดโปรตุเกส"},"MZE":{"name":"เอสคูโดโมซัมบิก"},"UAH":{"name":"ฮรีฟเนียยูเครน","symbolNarrow":"₴"},"KRH":{"name":"ฮวานเกาหลีใต้ (1953–1962)"},"CSK":{"name":"ฮาร์ดโครูนาเช็กโกสโลวัก"},"YUD":{"name":"ฮาร์ดดีนาร์ยูโกสลาเวีย"},"BGL":{"name":"ฮาร์ดเลฟบัลแกเรีย"},"ALK":{"name":"Albanian Lek (1946–1965)","pluralName":{"one":"Albanian lek (1946–1965)","other":"Albanian lekë (1946–1965)"}},"CNX":{"name":"Chinese People’s Bank Dollar","pluralName":{"one":"Chinese People’s Bank dollar","other":"Chinese People’s Bank dollars"}},"ISJ":{"name":"Icelandic Króna (1918–1981)","pluralName":{"one":"Icelandic króna (1918–1981)","other":"Icelandic krónur (1918–1981)"}},"ILR":{"name":"Israeli Shekel (1980–1985)","pluralName":{"one":"Israeli shekel (1980–1985)","other":"Israeli shekels (1980–1985)"}},"MVP":{"name":"Maldivian Rupee (1947–1981)","pluralName":{"one":"Maldivian rupee (1947–1981)","other":"Maldivian rupees (1947–1981)"}}}